genericoutput/__init__.py
genericoutput/notifier.py
genericoutput/assets/__init__.py
genericoutput/assets/file.py
genericoutput/assets/gasset.py
genericoutput/assets/html.py
genericoutput/assets/log.py
genericoutput/assets/picture.py
genericoutput/metadata/__init__.py
genericoutput/metadata/metadata.py
genericoutput/storages/__init__.py
genericoutput/storages/filesystem.py
genericoutput/storages/minio.py
genericoutput/storages/storage.py
generic_output_manager-0.1.1.dist-info/METADATA
generic_output_manager-0.1.1.dist-info/WHEEL
generic_output_manager-0.1.1.dist-info/top_level.txt
generic_output_manager-0.1.1.dist-info/RECORD
