Metadata-Version: 2.1
Name: generic-output-manager
Version: 0.1.1
Summary: UNKNOWN
Home-page: UNKNOWN
Author: Alida research team
Author-email: engineering-alida-lab@eng.it
License: UNKNOWN
Platform: UNKNOWN
Classifier: Programming Language :: Python :: 3
Classifier: License :: OSI Approved :: MIT License
Classifier: Operating System :: OS Independent
Requires-Python: >=3.6
Requires-Dist: bda-service-utils
Requires-Dist: minio
Requires-Dist: alida-arg-parser (>=0.0.35)
Requires-Dist: kafka-python (>=2.0.2)
